nbconvert_queue/__init__.py
nbconvert_queue/_version.py
nbconvert_queue/db_handler.py
nbconvert_queue/handlers.py
nbconvert_queue-0.1.0.data/data/etc/jupyter/jupyter_notebook_config.d/nbconvert_queue.json
nbconvert_queue-0.1.0.data/data/etc/jupyter/jupyter_server_config.d/nbconvert_queue.json
nbconvert_queue-0.1.0.data/data/share/jupyter/labextensions/nbconvert_queue/build_log.json
nbconvert_queue-0.1.0.data/data/share/jupyter/labextensions/nbconvert_queue/install.json
nbconvert_queue-0.1.0.data/data/share/jupyter/labextensions/nbconvert_queue/package.json
nbconvert_queue-0.1.0.data/data/share/jupyter/labextensions/nbconvert_queue/static/4dd3561bac1f21c70270e2f4d93e30b9eaa7538b5fb12b6f6d5d9a74033e5750.woff2
nbconvert_queue-0.1.0.data/data/share/jupyter/labextensions/nbconvert_queue/static/77df7d949de7b5ae43b0.woff2
nbconvert_queue-0.1.0.data/data/share/jupyter/labextensions/nbconvert_queue/static/8be134a2ed7f85fceac5.ttf
nbconvert_queue-0.1.0.data/data/share/jupyter/labextensions/nbconvert_queue/static/db04c49278de66fe78d2bfebf2ea48cea5ea5278071b87bb757d1fad6ad045f4.ttf
nbconvert_queue-0.1.0.data/data/share/jupyter/labextensions/nbconvert_queue/static/lib_index_js-data_image_svg_xml_3csvg_xmlns_27http_www_w3_org_2000_svg_27_viewBox_27-4_-4_8_8-ebac61.3fad158ff198e0983a0d.js
nbconvert_queue-0.1.0.data/data/share/jupyter/labextensions/nbconvert_queue/static/lib_index_js-data_image_svg_xml_3csvg_xmlns_27http_www_w3_org_2000_svg_27_viewBox_27-4_-4_8_8-ebac61.3fad158ff198e0983a0d.js.map
nbconvert_queue-0.1.0.data/data/share/jupyter/labextensions/nbconvert_queue/static/remoteEntry.40d515a5a703e137d76a.js
nbconvert_queue-0.1.0.data/data/share/jupyter/labextensions/nbconvert_queue/static/remoteEntry.40d515a5a703e137d76a.js.map
nbconvert_queue-0.1.0.data/data/share/jupyter/labextensions/nbconvert_queue/static/style.js
nbconvert_queue-0.1.0.dist-info/METADATA
nbconvert_queue-0.1.0.dist-info/WHEEL
nbconvert_queue-0.1.0.dist-info/licenses/LICENSE
nbconvert_queue-0.1.0.dist-info/RECORD
