Metadata-Version: 2.1
Name: nbconvert_queue
Version: 0.1.0
Summary: A JupyterLab extension for queuing notebooks executions.
Project-URL: Homepage, https://github.com/github_username/nbconvert_queue
Project-URL: Bug Tracker, https://github.com/github_username/nbconvert_queue/issues
Project-URL: Repository, https://github.com/github_username/nbconvert_queue.git
Author-email: Navteca LLC <info@navteca.com>
License: BSD 3-Clause License
License-File: LICENSE
Classifier: Framework :: Jupyter
Classifier: Framework :: Jupyter :: JupyterLab
Classifier: Framework :: Jupyter :: JupyterLab :: 4
Classifier: Framework :: Jupyter :: JupyterLab :: Extensions
Classifier: Framework :: Jupyter :: JupyterLab :: Extensions :: Prebuilt
Classifier: License :: OSI Approved :: BSD License
Classifier: Programming Language :: Python
Classifier: Programming Language :: Python :: 3
Classifier: Programming Language :: Python :: 3.8
Classifier: Programming Language :: Python :: 3.9
Classifier: Programming Language :: Python :: 3.10
Classifier: Programming Language :: Python :: 3.11
Requires-Python: >=3.8
Requires-Dist: jupyter-server<3,>=2.0.1
